fastapi_app_manage/__init__.py
fastapi_app_manage/code.py
fastapi_app_manage/enums.py
fastapi_app_manage/main.py
fastapi_app_manage/manage.py
fastapi_app_manage/utils/__init__.py
fastapi_app_manage/utils/__pycache__/__init__.cpython-311.pyc
fastapi_app_manage/utils/__pycache__/format.cpython-311.pyc
fastapi_app_manage/utils/__pycache__/get_package.cpython-311.pyc
fastapi_app_manage/utils/__pycache__/get_package_version.cpython-311.pyc
fastapi_app_manage/utils/__pycache__/typedict.cpython-311.pyc
fastapi_app_manage/utils/__pycache__/write_dict_2_toml_file.cpython-311.pyc
fastapi_app_manage/utils/format.py
fastapi_app_manage/utils/get_package.py
fastapi_app_manage/utils/typedict.py
fastapi_app_manage/write.py
fastapi_app_manage-4.0.2.dist-info/entry_points.txt
fastapi_app_manage-4.0.2.dist-info/METADATA
fastapi_app_manage-4.0.2.dist-info/WHEEL
fastapi_app_manage-4.0.2.dist-info/RECORD
